pyboletobr/__init__.py
pyboletobr/data.py
pyboletobr/html.py
pyboletobr/pdf.py
pyboletobr/bank/__init__.py
pyboletobr/bank/bancodobrasil.py
pyboletobr/bank/banrisul.py
pyboletobr/bank/bradesco.py
pyboletobr/bank/caixa.py
pyboletobr/bank/caixa_sigcb.py
pyboletobr/bank/hsbc.py
pyboletobr/bank/itau.py
pyboletobr/bank/real.py
pyboletobr/bank/santander.py
pyboletobr/bank/sicredi.py
pyboletobr/django/__init__.py
pyboletobr/django/admin.py
pyboletobr/django/models.py
pyboletobr/django/views.py
pyboletobr/media/logo_bancobradesco.jpg
pyboletobr/media/logo_bancocaixa.jpg
pyboletobr/media/logo_bancohsbc.jpg
pyboletobr/media/logo_bancoreal.jpg
pyboletobr/media/logo_banrisul.jpg
pyboletobr/media/logo_bb.jpg
pyboletobr/media/logo_itau.jpg
pyboletobr/media/logo_santander.jpg
pyboletobr/media/logo_sicredi.jpg
pyboletobr/templates/head.html
pyboletobr/templates/recibo_caixa.html
pyboletobr/templates/recibo_sacado.html
pyboletobr-0.5.3.data/scripts/html_pyboleto_sample.py
pyboletobr-0.5.3.data/scripts/pdf_pyboleto_sample.py
tests/__init__.py
tests/alltests.py
tests/test_banco_banrisul.py
tests/test_banco_bradesco.py
tests/test_banco_caixa.py
tests/test_banco_do_brasil.py
tests/test_banco_hsbc.py
tests/test_banco_hsbc_com_registro.py
tests/test_banco_itau.py
tests/test_banco_real.py
tests/test_banco_santander.py
tests/testutils.py
tests/xml/BoletoBB-expected.xml
tests/xml/BoletoBanrisul-expected.xml
tests/xml/BoletoBradesco-expected.xml
tests/xml/BoletoCaixa-expected.xml
tests/xml/BoletoHsbc-expected.xml
tests/xml/BoletoHsbcComRegistro-expected.xml
tests/xml/BoletoItau-expected.xml
tests/xml/BoletoReal-expected.xml
tests/xml/BoletoSantander-expected.xml
tests/xml/Triplo-BoletoBB-expected.xml
tests/xml/Triplo-BoletoBanrisul-expected.xml
tests/xml/Triplo-BoletoBradesco-expected.xml
tests/xml/Triplo-BoletoCaixa-expected.xml
tests/xml/Triplo-BoletoHsbc-expected.xml
tests/xml/Triplo-BoletoHsbcComRegistro-expected.xml
tests/xml/Triplo-BoletoItau-expected.xml
pyboletobr-0.5.3.dist-info/LICENSE
pyboletobr-0.5.3.dist-info/METADATA
pyboletobr-0.5.3.dist-info/WHEEL
pyboletobr-0.5.3.dist-info/top_level.txt
pyboletobr-0.5.3.dist-info/RECORD
