Metadata-Version: 2.1
Name: pyboletobr
Version: 0.5.3
Summary: Python Library to create "boletos de cobrança bancária" for     several Brazilian banks
Home-page: https://github.com/ericjmachado/pyboleto
Download-URL: http://pypi.python.org/pypi/pyboleto
Author: Eric de jesus machado
Author-email: ericmachadoeng@gmail.com
License: BSD
Platform: any
Classifier: Development Status :: 4 - Beta
Classifier: Operating System :: OS Independent
Classifier: Intended Audience :: Developers
Classifier: Intended Audience :: Financial and Insurance Industry
Classifier: Operating System :: OS Independent
Classifier: License :: OSI Approved :: BSD License
Classifier: Natural Language :: Portuguese (Brazilian)
Classifier: Programming Language :: Python
Classifier: Programming Language :: Python :: 3
Classifier: Programming Language :: Python :: 2.7
Classifier: Programming Language :: Python :: 2.6
Classifier: Topic :: Office/Business :: Financial
Classifier: Topic :: Software Development :: Libraries :: Python Modules
Classifier: Framework :: Django
Provides: pyboletobr
License-File: LICENSE
Requires-Dist: setuptools
Requires-Dist: reportlab
